pingping/__init__.py
pingping/ping.py
pingping-1.3.5.dist-info/METADATA
pingping-1.3.5.dist-info/WHEEL
pingping-1.3.5.dist-info/entry_points.txt
pingping-1.3.5.dist-info/licenses/LICENSE
pingping-1.3.5.dist-info/RECORD
