Metadata-Version: 2.4
Name: pingping
Version: 1.3.5
Summary: pingping is a special library which understands multi linguistic of ping output and translated the result to machine understandable format. Pingping support tcp-ping
Project-URL: Homepage, https://github.com/network-tools/pingping
Project-URL: Repository, https://github.com/network-tools/pingping
Project-URL: Issues, https://github.com/network-tools/pingping/issues
Author-email: Kiran Kumar Kotari <kirankotari@live.com>
License: MIT
License-File: LICENSE
Keywords: http ping,l4 ping,multi linguistic,ping,ping over proxy,tcp ping,web ping
Classifier: Development Status :: 5 - Production/Stable
Classifier: Intended Audience :: Developers
Classifier: License :: OSI Approved :: MIT License
Classifier: Programming Language :: Python :: 3
Classifier: Programming Language :: Python :: 3.9
Classifier: Programming Language :: Python :: 3.10
Classifier: Programming Language :: Python :: 3.11
Classifier: Programming Language :: Python :: 3.12
Classifier: Topic :: Software Development :: Build Tools
Requires-Python: >=3.9
Requires-Dist: shconfparser>=2.2.2
Requires-Dist: tcping>=0.1.1rc1
Provides-Extra: dev
Requires-Dist: black>=24.0.0; extra == 'dev'
Requires-Dist: pytest-cov>=4.1.0; extra == 'dev'
Requires-Dist: pytest>=8.0.0; extra == 'dev'
Requires-Dist: ruff>=0.8.0; extra == 'dev'
Requires-Dist: testiq>=0.2.0; extra == 'dev'
